[{"index": 1, "title": "\u8096\u7533\u514b\u7684\u6551\u8d4e", "director": ["\u5f17\u5170\u514b\u00b7\u5fb7\u62c9\u90a6\u7279 Frank Darabont"], "date": "1994", "region": ["\u7f8e\u56fd"], "genre": ["\u72af\u7f6a", "\u5267\u60c5"]}, {"index": 2, "title": "\u9738\u738b\u522b\u59ec", "director": ["\u9648\u51ef\u6b4c Kaige Chen"], "date": "1993", "region": ["\u4e2d\u56fd\u5927\u9646", "\u4e2d\u56fd\u9999\u6e2f"], "genre": ["\u5267\u60c5", "\u7231\u60c5", "\u540c\u6027"]}, {"index": 3, "title": "\u963f\u7518\u6b63\u4f20", "director": ["\u7f57\u4f2f\u7279\u00b7\u6cfd\u7c73\u5409\u65af Robert Zemeckis"], "date": "1994", "region": ["\u7f8e\u56fd"], "genre": ["\u5267\u60c5", "\u7231\u60c5"]}, {"index": 4, "title": "\u8fd9\u4e2a\u6740\u624b\u4e0d\u592a\u51b7", "director": ["\u5415\u514b\u00b7\u8d1d\u677e Luc Besson"], "date": "1994", "region": ["\u6cd5\u56fd", "\u7f8e\u56fd"], "genre": ["\u5267\u60c5", "\u52a8\u4f5c", "\u72af\u7f6a"]}, {"index": 5, "title": "\u6cf0\u5766\u5c3c\u514b\u53f7", "director": ["\u8a79\u59c6\u65af\u00b7\u5361\u6885\u9686 James Cameron"], "date": "1997", "region": ["\u7f8e\u56fd", "\u58a8\u897f\u54e5", "\u6fb3\u5927\u5229\u4e9a", "\u52a0\u62ff\u5927"], "genre": ["\u5267\u60c5", "\u7231\u60c5", "\u707e\u96be"]}, {"index": 6, "title": "\u7f8e\u4e3d\u4eba\u751f", "director": ["\u7f57\u4f2f\u6258\u00b7\u8d1d\u5c3c\u5c3c Roberto Benigni"], "date": "1997", "region": ["\u610f\u5927\u5229"], "genre": ["\u5267\u60c5", "\u559c\u5267", "\u7231\u60c5", "\u6218\u4e89"]}, {"index": 7, "title": "\u5343\u4e0e\u5343\u5bfb", "director": ["\u5bab\u5d0e\u9a8f Hayao Miyazaki"], "date": "2001", "region": ["\u65e5\u672c"], "genre": ["\u5267\u60c5", "\u52a8\u753b", "\u5947\u5e7b"]}, {"index": 8, "title": "\u8f9b\u5fb7\u52d2\u7684\u540d\u5355", "director": ["\u53f2\u8482\u6587\u00b7\u65af\u76ae\u5c14\u4f2f\u683c Steven Spielberg"], "date": "1993", "region": ["\u7f8e\u56fd"], "genre": ["\u5267\u60c5", "\u5386\u53f2", "\u6218\u4e89"]}, {"index": 9, "title": "\u76d7\u68a6\u7a7a\u95f4", "director": ["\u514b\u91cc\u65af\u6258\u5f17\u00b7\u8bfa\u5170 Christopher Nolan"], "date": "2010", "region": ["\u7f8e\u56fd", "\u82f1\u56fd"], "genre": ["\u5267\u60c5", "\u79d1\u5e7b", "\u60ac\u7591", "\u5192\u9669"]}, {"index": 10, "title": "\u5fe0\u72ac\u516b\u516c\u7684\u6545\u4e8b", "director": ["\u83b1\u585e\u00b7\u970d\u5c14\u65af\u9053\u59c6 Lasse Hallstr\u00f6m"], "date": "2009", "region": ["\u7f8e\u56fd", "\u82f1\u56fd"], "genre": ["\u5267\u60c5"]}, {"index": 11, "title": "\u661f\u9645\u7a7f\u8d8a", "director": ["\u514b\u91cc\u65af\u6258\u5f17\u00b7\u8bfa\u5170 Christopher Nolan"], "date": "2014", "region": ["\u7f8e\u56fd", "\u82f1\u56fd", "\u52a0\u62ff\u5927"], "genre": ["\u5267\u60c5", "\u79d1\u5e7b", "\u5192\u9669"]}, {"index": 12, "title": "\u695a\u95e8\u7684\u4e16\u754c", "director": ["\u5f7c\u5f97\u00b7\u5a01\u5c14 Peter Weir"], "date": "1998", "region": ["\u7f8e\u56fd"], "genre": ["\u5267\u60c5", "\u79d1\u5e7b"]}, {"index": 13, "title": "\u6d77\u4e0a\u94a2\u7434\u5e08", "director": ["\u6731\u585e\u4f69\u00b7\u6258\u7eb3\u591a\u96f7 Giuseppe Tornatore"], "date": "1998", "region": ["\u610f\u5927\u5229"], "genre": ["\u5267\u60c5", "\u97f3\u4e50"]}, {"index": 14, "title": "\u4e09\u50bb\u5927\u95f9\u5b9d\u83b1\u575e", "director": ["\u62c9\u5e93\u9a6c\u00b7\u5e0c\u62c9\u5c3c Rajkumar Hirani"], "date": "2009", "region": ["\u5370\u5ea6"], "genre": ["\u5267\u60c5", "\u559c\u5267", "\u7231\u60c5", "\u6b4c\u821e"]}, {"index": 15, "title": "\u673a\u5668\u4eba\u603b\u52a8\u5458", "director": ["\u5b89\u5fb7\u9c81\u00b7\u65af\u5766\u987f Andrew Stanton"], "date": "2008", "region": ["\u7f8e\u56fd"], "genre": ["\u79d1\u5e7b", "\u52a8\u753b", "\u5192\u9669"]}, {"index": 16, "title": "\u653e\u725b\u73ed\u7684\u6625\u5929", "director": ["\u514b\u91cc\u65af\u6258\u592b\u00b7\u5df4\u62c9\u8482 Christophe Barratier"], "date": "2004", "region": ["\u6cd5\u56fd", "\u745e\u58eb", "\u5fb7\u56fd"], "genre": ["\u5267\u60c5", "\u559c\u5267", "\u97f3\u4e50"]}, {"index": 17, "title": "\u65e0\u95f4\u9053", "director": ["\u5218\u4f1f\u5f3a", "\u9ea6\u5146\u8f89"], "date": "2002", "region": ["\u4e2d\u56fd\u9999\u6e2f"], "genre": ["\u5267\u60c5", "\u72af\u7f6a", "\u60ca\u609a"]}, {"index": 18, "title": "\u75af\u72c2\u52a8\u7269\u57ce", "director": ["\u62dc\u4f26\u00b7\u970d\u534e\u5fb7 Byron Howard", "\u745e\u5947\u00b7\u6469\u5c14 Rich Moore"], "date": "2016", "region": ["\u7f8e\u56fd"], "genre": ["\u559c\u5267", "\u52a8\u753b", "\u5192\u9669"]}, {"index": 19, "title": "\u5927\u8bdd\u897f\u6e38\u4e4b\u5927\u5723\u5a36\u4eb2", "director": ["\u5218\u9547\u4f1f Jeffrey Lau"], "date": "1995", "region": ["\u4e2d\u56fd\u9999\u6e2f", "\u4e2d\u56fd\u5927\u9646"], "genre": ["\u559c\u5267", "\u7231\u60c5", "\u5947\u5e7b", "\u53e4\u88c5"]}, {"index": 20, "title": "\u7194\u7089", "director": ["\u9ec4\u4e1c\u8d6b Dong-hyuk Hwang"], "date": "2011", "region": ["\u97e9\u56fd"], "genre": ["\u5267\u60c5"]}, {"index": 21, "title": "\u6559\u7236", "director": ["\u5f17\u6717\u897f\u65af\u00b7\u798f\u7279\u00b7\u79d1\u6ce2\u62c9 Francis Ford Coppola"], "date": "1972", "region": ["\u7f8e\u56fd"], "genre": ["\u5267\u60c5", "\u72af\u7f6a"]}, {"index": 22, "title": "\u5f53\u5e78\u798f\u6765\u6572\u95e8", "director": ["\u52a0\u5e03\u91cc\u5c14\u00b7\u7a46\u5947\u8bfa Gabriele Muccino"], "date": "2006", "region": ["\u7f8e\u56fd"], "genre": ["\u5267\u60c5", "\u4f20\u8bb0", "\u5bb6\u5ead"]}, {"index": 23, "title": "\u9f99\u732b", "director": ["\u5bab\u5d0e\u9a8f Hayao Miyazaki"], "date": "1988", "region": ["\u65e5\u672c"], "genre": ["\u52a8\u753b", "\u5947\u5e7b", "\u5192\u9669"]}, {"index": 24, "title": "\u6026\u7136\u5fc3\u52a8", "director": ["\u7f57\u4f2f\u00b7\u83b1\u7eb3 Rob Reiner"], "date": "2010", "region": ["\u7f8e\u56fd"], "genre": ["\u5267\u60c5", "\u559c\u5267", "\u7231\u60c5"]}, {"index": 25, "title": "\u63a7\u65b9\u8bc1\u4eba", "director": ["\u6bd4\u5229\u00b7\u6000\u5c14\u5fb7 Billy Wilder"], "date": "1957", "region": ["\u7f8e\u56fd"], "genre": ["\u5267\u60c5", "\u72af\u7f6a", "\u60ac\u7591"]}, {"index": 26, "title": "\u89e6\u4e0d\u53ef\u53ca", "director": ["\u5965\u5229\u7ef4\u00b7\u90a3\u5361\u4ec0 Olivier Nakache", "\u827e\u529b\u514b\u00b7\u6258\u5170\u8fbe Eric Toledano"], "date": "2011", "region": ["\u6cd5\u56fd"], "genre": ["\u5267\u60c5", "\u559c\u5267"]}, {"index": 27, "title": "\u8759\u8760\u4fa0\uff1a\u9ed1\u6697\u9a91\u58eb", "director": ["\u514b\u91cc\u65af\u6258\u5f17\u00b7\u8bfa\u5170 Christopher Nolan"], "date": "2008", "region": ["\u7f8e\u56fd", "\u82f1\u56fd"], "genre": ["\u5267\u60c5", "\u52a8\u4f5c", "\u79d1\u5e7b", "\u72af\u7f6a", "\u60ca\u609a"]}, {"index": 28, "title": "\u672b\u4ee3\u7687\u5e1d", "director": ["\u8d1d\u7eb3\u5c14\u591a\u00b7\u8d1d\u6258\u9c81\u5947 Bernardo Bertolucci"], "date": "1987", "region": ["\u82f1\u56fd", "\u610f\u5927\u5229", "\u4e2d\u56fd\u5927\u9646", "\u6cd5\u56fd"], "genre": ["\u5267\u60c5", "\u4f20\u8bb0", "\u5386\u53f2"]}, {"index": 29, "title": "\u5bfb\u68a6\u73af\u6e38\u8bb0", "director": ["\u674e\u00b7\u6602\u514b\u91cc\u5947 Lee Unkrich", "\u963f\u5fb7\u91cc\u5b89\u00b7\u83ab\u5229\u7eb3 Adrian Molina"], "date": "2017", "region": ["\u7f8e\u56fd"], "genre": ["\u559c\u5267", "\u52a8\u753b", "\u5947\u5e7b", "\u97f3\u4e50"]}, {"index": 30, "title": "\u6d3b\u7740", "director": ["\u5f20\u827a\u8c0b Yimou Zhang"], "date": "1994", "region": ["\u4e2d\u56fd\u5927\u9646", "\u4e2d\u56fd\u9999\u6e2f"], "genre": ["\u5267\u60c5", "\u5386\u53f2", "\u5bb6\u5ead"]}, {"index": 31, "title": "\u6307\u73af\u738b3\uff1a\u738b\u8005\u65e0\u654c", "director": ["\u5f7c\u5f97\u00b7\u6770\u514b\u900a Peter Jackson"], "date": "2003", "region": ["\u7f8e\u56fd", "\u65b0\u897f\u5170"], "genre": ["\u5267\u60c5", "\u52a8\u4f5c", "\u5947\u5e7b", "\u5192\u9669"]}, {"index": 32, "title": "\u4e71\u4e16\u4f73\u4eba", "director": ["\u7ef4\u514b\u591a\u00b7\u5f17\u83b1\u660e Victor Fleming", "\u4e54\u6cbb\u00b7\u5e93\u514b George Cukor"], "date": "1939", "region": ["\u7f8e\u56fd"], "genre": ["\u5267\u60c5", "\u5386\u53f2", "\u7231\u60c5", "\u6218\u4e89"]}, {"index": 33, "title": "\u4f55\u4ee5\u4e3a\u5bb6", "director": ["\u5a1c\u4e01\u00b7\u62c9\u5df4\u57fa Nadine Labaki"], "date": "2018", "region": ["\u9ece\u5df4\u5ae9", "\u7f8e\u56fd", "\u6cd5\u56fd", "\u585e\u6d66\u8def\u65af", "\u5361\u5854\u5c14", "\u82f1\u56fd"], "genre": ["\u5267\u60c5"]}, {"index": 34, "title": "\u54c8\u5229\u00b7\u6ce2\u7279\u4e0e\u9b54\u6cd5\u77f3", "director": ["Chris Columbus"], "date": "2001", "region": ["\u7f8e\u56fd", "\u82f1\u56fd"], "genre": ["\u5947\u5e7b", "\u5192\u9669"]}, {"index": 35, "title": "\u98de\u5c4b\u73af\u6e38\u8bb0", "director": ["\u5f7c\u7279\u00b7\u9053\u683c\u7279 Pete Docter", "\u9c8d\u52c3\u00b7\u5f7c\u5fb7\u68ee Bob Peterson"], "date": "2009", "region": ["\u7f8e\u56fd"], "genre": ["\u5267\u60c5", "\u559c\u5267", "\u52a8\u753b", "\u5192\u9669"]}, {"index": 36, "title": "\u7d20\u5a9b", "director": ["\u674e\u6fec\u76ca Jun-ik Lee"], "date": "2013", "region": ["\u97e9\u56fd"], "genre": ["\u5267\u60c5"]}, {"index": 37, "title": "\u6454\u8de4\u5427\uff01\u7238\u7238", "director": ["\u6d85\u63d0\u00b7\u8482\u74e6\u91cc Nitesh Tiwari"], "date": "2016", "region": ["\u5370\u5ea6"], "genre": ["\u5267\u60c5", "\u4f20\u8bb0", "\u8fd0\u52a8", "\u5bb6\u5ead"]}, {"index": 38, "title": "\u5c11\u5e74\u6d3e\u7684\u5947\u5e7b\u6f02\u6d41", "director": ["\u674e\u5b89 Ang Lee"], "date": "2012", "region": ["\u7f8e\u56fd", "\u4e2d\u56fd\u53f0\u6e7e", "\u82f1\u56fd", "\u52a0\u62ff\u5927"], "genre": ["\u5267\u60c5", "\u5947\u5e7b", "\u5192\u9669"]}, {"index": 39, "title": "\u5341\u4e8c\u6012\u6c49", "director": ["Sidney Lumet"], "date": "1957", "region": ["\u7f8e\u56fd"], "genre": ["\u5267\u60c5"]}, {"index": 40, "title": "\u54c8\u5c14\u7684\u79fb\u52a8\u57ce\u5821", "director": ["\u5bab\u5d0e\u9a8f Hayao Miyazaki"], "date": "2004", "region": ["\u65e5\u672c"], "genre": ["\u52a8\u753b", "\u5947\u5e7b", "\u5192\u9669"]}, {"index": 41, "title": "\u9b3c\u5b50\u6765\u4e86", "director": ["\u59dc\u6587 Wen Jiang"], "date": "2000", "region": ["\u4e2d\u56fd\u5927\u9646"], "genre": ["\u5267\u60c5", "\u559c\u5267"]}, {"index": 42, "title": "\u6211\u4e0d\u662f\u836f\u795e", "director": ["\u6587\u7267\u91ce Muye Wen"], "date": "2018", "region": ["\u4e2d\u56fd\u5927\u9646"], "genre": ["\u5267\u60c5", "\u559c\u5267"]}, {"index": 43, "title": "\u5927\u8bdd\u897f\u6e38\u4e4b\u6708\u5149\u5b9d\u76d2", "director": ["\u5218\u9547\u4f1f Jeffrey Lau"], "date": "1995", "region": ["\u4e2d\u56fd\u9999\u6e2f", "\u4e2d\u56fd\u5927\u9646"], "genre": ["\u559c\u5267", "\u7231\u60c5", "\u5947\u5e7b", "\u53e4\u88c5"]}, {"index": 44, "title": "\u5929\u7a7a\u4e4b\u57ce", "director": ["\u5bab\u5d0e\u9a8f Hayao Miyazaki"], "date": "1986", "region": ["\u65e5\u672c"], "genre": ["\u52a8\u753b", "\u5947\u5e7b", "\u5192\u9669"]}, {"index": 45, "title": "\u5929\u5802\u7535\u5f71\u9662", "director": ["\u6731\u585e\u4f69\u00b7\u6258\u7eb3\u591a\u96f7 Giuseppe Tornatore"], "date": "1988", "region": ["\u610f\u5927\u5229", "\u6cd5\u56fd"], "genre": ["\u5267\u60c5", "\u7231\u60c5"]}, {"index": 46, "title": "\u95fb\u9999\u8bc6\u5973\u4eba", "director": ["\u9a6c\u4e01\u00b7\u5e03\u83b1\u65af Martin Brest"], "date": "1992", "region": ["\u7f8e\u56fd"], "genre": ["\u5267\u60c5"]}, {"index": 47, "title": "\u7f57\u9a6c\u5047\u65e5", "director": ["\u5a01\u5ec9\u00b7\u60e0\u52d2 William Wyler"], "date": "1953", "region": ["\u7f8e\u56fd"], "genre": ["\u559c\u5267", "\u5267\u60c5", "\u7231\u60c5"]}, {"index": 48, "title": "\u6307\u73af\u738b2\uff1a\u53cc\u5854\u5947\u5175", "director": ["\u5f7c\u5f97\u00b7\u6770\u514b\u900a Peter Jackson"], "date": "2002", "region": ["\u7f8e\u56fd", "\u65b0\u897f\u5170"], "genre": ["\u5267\u60c5", "\u52a8\u4f5c", "\u5947\u5e7b", "\u5192\u9669"]}, {"index": 49, "title": "\u732b\u9f20\u6e38\u620f", "director": ["\u53f2\u8482\u6587\u00b7\u65af\u76ae\u5c14\u4f2f\u683c Steven Spielberg"], "date": "2002", "region": ["\u7f8e\u56fd", "\u52a0\u62ff\u5927"], "genre": ["\u4f20\u8bb0", "\u72af\u7f6a", "\u5267\u60c5"]}, {"index": 50, "title": "\u8fa9\u62a4\u4eba", "director": ["\u6768\u5b87\u7855 Woo-seok Yang"], "date": "2013", "region": ["\u97e9\u56fd"], "genre": ["\u5267\u60c5"]}, {"index": 51, "title": "\u6307\u73af\u738b1\uff1a\u62a4\u6212\u4f7f\u8005", "director": ["\u5f7c\u5f97\u00b7\u6770\u514b\u900a Peter Jackson"], "date": "2001", "region": ["\u65b0\u897f\u5170", "\u7f8e\u56fd"], "genre": ["\u5267\u60c5", "\u52a8\u4f5c", "\u5947\u5e7b", "\u5192\u9669"]}, {"index": 52, "title": "\u5927\u95f9\u5929\u5bab", "director": ["\u4e07\u7c41\u9e23 Laiming Wan"], "date": "0", "region": [], "genre": []}, {"index": 53, "title": "\u94a2\u7434\u5bb6", "director": ["\u7f57\u66fc\u00b7\u6ce2\u5170\u65af\u57fa Roman Polanski"], "date": "2002", "region": ["\u82f1\u56fd", "\u6cd5\u56fd", "\u6ce2\u5170", "\u5fb7\u56fd", "\u7f8e\u56fd"], "genre": ["\u5267\u60c5", "\u4f20\u8bb0", "\u6218\u4e89", "\u97f3\u4e50"]}, {"index": 54, "title": "\u72ee\u5b50\u738b", "director": ["Roger Allers", "\u7f57\u4f2f\u00b7\u660e\u53ef\u592b Rob Minkoff"], "date": "1994", "region": ["\u7f8e\u56fd"], "genre": ["\u52a8\u753b", "\u5192\u9669", "\u6b4c\u821e"]}, {"index": 55, "title": "\u6559\u72362", "director": ["\u5f17\u6717\u897f\u65af\u00b7\u798f\u7279\u00b7\u79d1\u6ce2\u62c9 Francis Ford Coppola"], "date": "1974", "region": ["\u7f8e\u56fd"], "genre": ["\u5267\u60c5", "\u72af\u7f6a"]}, {"index": 56, "title": "\u6b7b\u4ea1\u8bd7\u793e", "director": ["\u5f7c\u5f97\u00b7\u5a01\u5c14 Peter Weir"], "date": "1989", "region": ["\u7f8e\u56fd"], "genre": ["\u5267\u60c5"]}, {"index": 57, "title": "\u640f\u51fb\u4ff1\u4e50\u90e8", "director": ["\u5927\u536b\u00b7\u82ac\u5947 David Fincher"], "date": "1999", "region": ["\u7f8e\u56fd", "\u5fb7\u56fd", "\u610f\u5927\u5229"], "genre": ["\u5267\u60c5", "\u52a8\u4f5c", "\u60ac\u7591", "\u60ca\u609a"]}, {"index": 58, "title": "\u8ba9\u5b50\u5f39\u98de", "director": ["\u59dc\u6587 Wen Jiang"], "date": "2010", "region": ["\u4e2d\u56fd\u5927\u9646", "\u4e2d\u56fd\u9999\u6e2f"], "genre": ["\u5267\u60c5", "\u559c\u5267", "\u52a8\u4f5c", "\u897f\u90e8"]}, {"index": 59, "title": "\u9ed1\u5ba2\u5e1d\u56fd", "director": ["\u5b89\u8fea\u00b7\u6c83\u5353\u65af\u57fa Andy Wachowski", "\u62c9\u5a1c\u00b7\u6c83\u5353\u65af\u57fa Lana Wachowski"], "date": "1999", "region": ["\u7f8e\u56fd"], "genre": ["\u52a8\u4f5c", "\u79d1\u5e7b"]}, {"index": 60, "title": "\u7eff\u76ae\u4e66", "director": ["\u5f7c\u5f97\u00b7\u6cd5\u96f7\u91cc Peter Farrelly"], "date": "2018", "region": ["\u7f8e\u56fd", "\u4e2d\u56fd\u5927\u9646"], "genre": ["\u5267\u60c5", "\u559c\u5267", "\u4f20\u8bb0", "\u97f3\u4e50"]}, {"index": 61, "title": "\u996e\u98df\u7537\u5973", "director": ["\u674e\u5b89 Ang Lee"], "date": "1994", "region": ["\u4e2d\u56fd\u53f0\u6e7e", "\u7f8e\u56fd"], "genre": ["\u5267\u60c5", "\u5bb6\u5ead"]}, {"index": 62, "title": "\u7f8e\u4e3d\u5fc3\u7075", "director": ["\u6717\u00b7\u970d\u534e\u5fb7 Ron Howard"], "date": "2001", "region": ["\u7f8e\u56fd"], "genre": ["\u4f20\u8bb0", "\u5267\u60c5"]}, {"index": 63, "title": "\u6d77\u8482\u548c\u7237\u7237", "director": ["\u963f\u5170\u00b7\u845b\u65af\u5f6d\u7eb3 Alain Gsponer"], "date": "2015", "region": ["\u5fb7\u56fd", "\u745e\u58eb"], "genre": ["\u5267\u60c5", "\u5192\u9669", "\u5bb6\u5ead"]}, {"index": 64, "title": "\u7a83\u542c\u98ce\u66b4", "director": ["\u5f17\u6d1b\u91cc\u5b89\u00b7\u4ea8\u514b\u5c14\u00b7\u51af\u00b7\u591a\u7eb3\u65af\u9a6c\u5c14\u514b Florian Henckel von Donnersmarck"], "date": "2006", "region": ["\u5fb7\u56fd"], "genre": ["\u5267\u60c5", "\u60ac\u7591"]}, {"index": 65, "title": "\u4e24\u6746\u5927\u70df\u67aa", "director": ["Guy Ritchie"], "date": "1998", "region": ["\u82f1\u56fd"], "genre": ["\u5267\u60c5", "\u559c\u5267", "\u72af\u7f6a"]}, {"index": 66, "title": "\u672c\u6770\u660e\u00b7\u5df4\u987f\u5947\u4e8b", "director": ["\u5927\u536b\u00b7\u82ac\u5947 David Fincher"], "date": "2008", "region": ["\u7f8e\u56fd"], "genre": ["\u5267\u60c5", "\u7231\u60c5", "\u5947\u5e7b"]}, {"index": 67, "title": "\u60c5\u4e66", "director": ["\u5ca9\u4e95\u4fca\u4e8c Shunji Iwai"], "date": "1995", "region": ["\u65e5\u672c"], "genre": ["\u5267\u60c5", "\u7231\u60c5"]}, {"index": 68, "title": "\u770b\u4e0d\u89c1\u7684\u5ba2\u4eba", "director": ["\u5965\u91cc\u5965\u5c14\u00b7\u4fdd\u7f57 Oriol Paulo"], "date": "2016", "region": ["\u897f\u73ed\u7259"], "genre": ["\u5267\u60c5", "\u72af\u7f6a", "\u60ac\u7591", "\u60ca\u609a"]}, {"index": 69, "title": "\u98de\u8d8a\u75af\u4eba\u9662", "director": ["\u7c73\u6d1b\u65af\u00b7\u798f\u5c14\u66fc Milo\u0161 Forman"], "date": "1975", "region": ["\u7f8e\u56fd"], "genre": ["\u5267\u60c5"]}, {"index": 70, "title": "\u7a7f\u6761\u7eb9\u7761\u8863\u7684\u7537\u5b69", "director": ["\u9a6c\u514b\u00b7\u8d6b\u5c14\u66fc Mark Herman"], "date": "2008", "region": ["\u82f1\u56fd", "\u7f8e\u56fd"], "genre": ["\u5267\u60c5", "\u6218\u4e89"]}, {"index": 71, "title": "\u897f\u897f\u91cc\u7684\u7f8e\u4e3d\u4f20\u8bf4", "director": ["\u6731\u585e\u4f69\u00b7\u6258\u7eb3\u591a\u96f7 Giuseppe Tornatore"], "date": "2000", "region": ["\u610f\u5927\u5229", "\u7f8e\u56fd"], "genre": ["\u5267\u60c5", "\u6218\u4e89", "\u60c5\u8272"]}, {"index": 72, "title": "\u62ef\u6551\u5927\u5175\u745e\u6069", "director": ["\u53f2\u8482\u6587\u00b7\u65af\u76ae\u5c14\u4f2f\u683c Steven Spielberg"], "date": "1998", "region": ["\u7f8e\u56fd"], "genre": ["\u5267\u60c5", "\u6218\u4e89"]}, {"index": 73, "title": "\u5c0f\u978b\u5b50", "director": ["\u9a6c\u57fa\u5fb7\u00b7\u9a6c\u57fa\u8fea Majid Majidi"], "date": "1997", "region": ["\u4f0a\u6717"], "genre": ["\u5267\u60c5", "\u513f\u7ae5", "\u5bb6\u5ead"]}, {"index": 74, "title": "\u97f3\u4e50\u4e4b\u58f0", "director": ["\u7f57\u4f2f\u7279\u00b7\u6000\u65af Robert Wise"], "date": "1965", "region": ["\u7f8e\u56fd"], "genre": ["\u5267\u60c5", "\u4f20\u8bb0", "\u7231\u60c5", "\u6b4c\u821e"]}, {"index": 75, "title": "\u963f\u51e1\u8fbe", "director": ["\u8a79\u59c6\u65af\u00b7\u5361\u6885\u9686 James Cameron"], "date": "2009", "region": ["\u7f8e\u56fd"], "genre": ["\u52a8\u4f5c", "\u79d1\u5e7b", "\u5192\u9669"]}, {"index": 76, "title": "\u6d77\u8c5a\u6e7e", "director": ["\u8def\u6613\u00b7\u897f\u970d\u5c24\u65af Louie Psihoyos"], "date": "2009", "region": ["\u7f8e\u56fd"], "genre": ["\u7eaa\u5f55\u7247"]}, {"index": 77, "title": "\u81f4\u547d\u9b54\u672f", "director": ["\u514b\u91cc\u65af\u6258\u5f17\u00b7\u8bfa\u5170 Christopher Nolan"], "date": "2006", "region": ["\u82f1\u56fd", "\u7f8e\u56fd"], "genre": ["\u5267\u60c5", "\u60ac\u7591", "\u60ca\u609a"]}, {"index": 78, "title": "\u7f8e\u56fd\u5f80\u4e8b", "director": ["\u8d5b\u5c14\u4e54\u00b7\u83b1\u7fc1\u5185 Sergio Leone"], "date": "1984", "region": ["\u7f8e\u56fd", "\u610f\u5927\u5229"], "genre": ["\u72af\u7f6a", "\u5267\u60c5"]}, {"index": 79, "title": "\u6c89\u9ed8\u7684\u7f94\u7f8a", "director": ["\u4e54\u7eb3\u68ee\u00b7\u6234\u7c73 Jonathan Demme"], "date": "1991", "region": ["\u7f8e\u56fd"], "genre": ["\u5267\u60c5", "\u72af\u7f6a", "\u60ca\u609a"]}, {"index": 80, "title": "\u7981\u95ed\u5c9b", "director": ["Martin Scorsese"], "date": "2010", "region": ["\u7f8e\u56fd"], "genre": ["\u5267\u60c5", "\u60ac\u7591", "\u60ca\u609a"]}, {"index": 81, "title": "\u8774\u8776\u6548\u5e94", "director": ["\u57c3\u91cc\u514b\u00b7\u5e03\u96f7\u65af Eric Bress", "J\u00b7\u9ea6\u57fa\u00b7\u683c\u9c81\u4f2f J. Mackye Gruber"], "date": "2004", "region": ["\u7f8e\u56fd", "\u52a0\u62ff\u5927"], "genre": ["\u5267\u60c5", "\u60ac\u7591", "\u79d1\u5e7b", "\u60ca\u609a"]}, {"index": 82, "title": "\u4f4e\u4fd7\u5c0f\u8bf4", "director": ["\u6606\u6c40\u00b7\u5854\u4f26\u8482\u8bfa Quentin Tarantino"], "date": "1994", "region": ["\u7f8e\u56fd"], "genre": ["\u5267\u60c5", "\u559c\u5267", "\u72af\u7f6a"]}, {"index": 83, "title": "\u5fc3\u7075\u6355\u624b", "director": ["\u683c\u65af\u00b7\u8303\u00b7\u6851\u7279 Gus Van Sant"], "date": "1997", "region": ["\u7f8e\u56fd"], "genre": ["\u5267\u60c5"]}, {"index": 84, "title": "\u5e03\u8fbe\u4f69\u65af\u5927\u996d\u5e97", "director": ["\u97e6\u65af\u00b7\u5b89\u5fb7\u68ee Wes Anderson"], "date": "2014", "region": ["\u7f8e\u56fd", "\u5fb7\u56fd", "\u82f1\u56fd"], "genre": ["\u5267\u60c5", "\u559c\u5267", "\u5192\u9669"]}, {"index": 85, "title": "\u6625\u5149\u4e4d\u6cc4", "director": ["\u738b\u5bb6\u536b Kar Wai Wong"], "date": "1997", "region": ["\u4e2d\u56fd\u9999\u6e2f", "\u65e5\u672c", "\u97e9\u56fd"], "genre": ["\u5267\u60c5", "\u7231\u60c5", "\u540c\u6027"]}, {"index": 86, "title": "\u4e03\u5b97\u7f6a", "director": ["\u5927\u536b\u00b7\u82ac\u5947 David Fincher"], "date": "1995", "region": ["\u7f8e\u56fd"], "genre": ["\u5267\u60c5", "\u72af\u7f6a", "\u60ac\u7591", "\u60ca\u609a"]}, {"index": 87, "title": "\u54c8\u5229\u00b7\u6ce2\u7279\u4e0e\u6b7b\u4ea1\u5723\u5668(\u4e0b)", "director": ["\u5927\u536b\u00b7\u53f6\u8328 David Yates"], "date": "2011", "region": ["\u7f8e\u56fd", "\u82f1\u56fd"], "genre": ["\u5947\u5e7b", "\u5192\u9669"]}, {"index": 88, "title": "\u6469\u767b\u65f6\u4ee3", "director": ["\u67e5\u7406\u00b7\u5353\u522b\u6797 Charles Chaplin"], "date": "1936", "region": ["\u7f8e\u56fd"], "genre": ["\u5267\u60c5", "\u559c\u5267", "\u7231\u60c5"]}, {"index": 89, "title": "\u559c\u5267\u4e4b\u738b", "director": ["\u5468\u661f\u9a70 Stephen Chow", "\u674e\u529b\u6301 Lik-Chi Lee"], "date": "1999", "region": ["\u4e2d\u56fd\u9999\u6e2f"], "genre": ["\u559c\u5267", "\u5267\u60c5", "\u7231\u60c5"]}, {"index": 90, "title": "\u88ab\u5acc\u5f03\u7684\u677e\u5b50\u7684\u4e00\u751f", "director": ["\u4e2d\u5c9b\u54f2\u4e5f Tetsuya Nakashima"], "date": "2006", "region": ["\u65e5\u672c"], "genre": ["\u5267\u60c5", "\u6b4c\u821e"]}, {"index": 91, "title": "\u81f4\u547dID", "director": ["\u8a79\u59c6\u65af\u00b7\u66fc\u9ad8\u5fb7 James Mangold"], "date": "2003", "region": ["\u7f8e\u56fd"], "genre": ["\u5267\u60c5", "\u60ac\u7591", "\u60ca\u609a"]}, {"index": 92, "title": "\u6740\u4eba\u56de\u5fc6", "director": ["\u5949\u4fca\u660a Joon-ho Bong"], "date": "2003", "region": ["\u97e9\u56fd"], "genre": ["\u5267\u60c5", "\u52a8\u4f5c", "\u72af\u7f6a", "\u60ac\u7591", "\u60ca\u609a"]}, {"index": 93, "title": "\u52a0\u52d2\u6bd4\u6d77\u76d7", "director": ["\u6208\u5c14\u00b7\u7ef4\u5bbe\u65af\u57fa Gore Verbinski"], "date": "2003", "region": ["\u7f8e\u56fd"], "genre": ["\u52a8\u4f5c", "\u5192\u9669", "\u5947\u5e7b"]}, {"index": 94, "title": "\u526a\u5200\u624b\u7231\u5fb7\u534e", "director": ["\u8482\u59c6\u00b7\u6ce2\u987f Tim Burton"], "date": "1990", "region": ["\u7f8e\u56fd"], "genre": ["\u5267\u60c5", "\u5947\u5e7b", "\u7231\u60c5"]}, {"index": 95, "title": "\u52c7\u6562\u7684\u5fc3", "director": ["\u6885\u5c14\u00b7\u5409\u5e03\u68ee Mel Gibson"], "date": "1995", "region": ["\u7f8e\u56fd"], "genre": ["\u52a8\u4f5c", "\u4f20\u8bb0", "\u5267\u60c5", "\u5386\u53f2", "\u6218\u4e89"]}, {"index": 96, "title": "\u72e9\u730e", "director": ["\u6258\u9a6c\u65af\u00b7\u6e29\u7279\u4f2f\u683c Thomas Vinterberg"], "date": "2012", "region": ["\u4e39\u9ea6", "\u745e\u5178"], "genre": ["\u5267\u60c5"]}, {"index": 97, "title": "\u8bf7\u4ee5\u4f60\u7684\u540d\u5b57\u547c\u5524\u6211", "director": ["\u5362\u5361\u00b7\u74dc\u8fbe\u5c3c\u8bfa Luca Guadagnino"], "date": "2017", "region": ["\u610f\u5927\u5229", "\u6cd5\u56fd", "\u5df4\u897f", "\u7f8e\u56fd", "\u8377\u5170", "\u5fb7\u56fd"], "genre": ["\u5267\u60c5", "\u7231\u60c5", "\u540c\u6027"]}, {"index": 98, "title": "\u7ea2\u8fa3\u6912", "director": ["\u4eca\u654f Satoshi Kon"], "date": "2006", "region": ["\u65e5\u672c"], "genre": ["\u52a8\u753b", "\u60ac\u7591", "\u79d1\u5e7b", "\u60ca\u609a"]}, {"index": 99, "title": "\u65ad\u80cc\u5c71", "director": ["\u674e\u5b89 Ang Lee"], "date": "2005", "region": ["\u7f8e\u56fd", "\u52a0\u62ff\u5927"], "genre": ["\u5267\u60c5", "\u7231\u60c5", "\u540c\u6027", "\u5bb6\u5ead"]}, {"index": 100, "title": "7\u53f7\u623f\u7684\u793c\u7269", "director": ["\u674e\u7115\u5e86 Hwan-kyeong Lee"], "date": "2013", "region": ["\u97e9\u56fd"], "genre": ["\u5267\u60c5", "\u559c\u5267", "\u5bb6\u5ead"]}, {"index": 101, "title": "\u5929\u4f7f\u7231\u7f8e\u4e3d", "director": ["\u8ba9-\u76ae\u57c3\u5c14\u00b7\u70ed\u5185 Jean-Pierre Jeunet"], "date": "2001", "region": ["\u6cd5\u56fd", "\u5fb7\u56fd"], "genre": ["\u5267\u60c5", "\u559c\u5267", "\u7231\u60c5"]}, {"index": 102, "title": "\u5e7d\u7075\u516c\u4e3b", "director": ["\u5bab\u5d0e\u9a8f Hayao Miyazaki"], "date": "1997", "region": ["\u65e5\u672c"], "genre": ["\u52a8\u753b", "\u5947\u5e7b", "\u5192\u9669"]}, {"index": 103, "title": "\u5c0f\u68ee\u6797 \u590f\u79cb\u7bc7", "director": ["\u68ee\u6df3\u4e00 Junichi Mori"], "date": "2014", "region": ["\u65e5\u672c"], "genre": ["\u5267\u60c5"]}, {"index": 104, "title": "\u8d85\u8131", "director": ["\u6258\u5c3c\u00b7\u51ef\u8036 Tony Kaye"], "date": "2011", "region": ["\u7f8e\u56fd"], "genre": ["\u5267\u60c5"]}, {"index": 105, "title": "\u7b2c\u516d\u611f", "director": ["M\u00b7\u5948\u7279\u00b7\u6c99\u9a6c\u5170 M. Night Shyamalan"], "date": "1999", "region": ["\u7f8e\u56fd"], "genre": ["\u5267\u60c5", "\u60ac\u7591", "\u60ca\u609a"]}, {"index": 106, "title": "\u529f\u592b", "director": ["\u5468\u661f\u9a70 Stephen Chow"], "date": "2004", "region": ["\u4e2d\u56fd\u5927\u9646", "\u4e2d\u56fd\u9999\u6e2f"], "genre": ["\u52a8\u4f5c", "\u559c\u5267", "\u72af\u7f6a", "\u5947\u5e7b"]}, {"index": 107, "title": "\u9633\u5149\u707f\u70c2\u7684\u65e5\u5b50", "director": ["\u59dc\u6587 Wen Jiang"], "date": "1994", "region": ["\u4e2d\u56fd\u5927\u9646", "\u4e2d\u56fd\u9999\u6e2f"], "genre": ["\u5267\u60c5", "\u7231\u60c5"]}, {"index": 108, "title": "\u91cd\u5e86\u68ee\u6797", "director": ["\u738b\u5bb6\u536b Kar Wai Wong"], "date": "1994", "region": ["\u4e2d\u56fd\u9999\u6e2f"], "genre": ["\u5267\u60c5", "\u7231\u60c5"]}, {"index": 109, "title": "\u5510\u4f2f\u864e\u70b9\u79cb\u9999", "director": ["\u674e\u529b\u6301 Lik-Chi Lee"], "date": "1993", "region": ["\u4e2d\u56fd\u9999\u6e2f"], "genre": ["\u559c\u5267", "\u7231\u60c5", "\u53e4\u88c5"]}, {"index": 110, "title": "\u7231\u5728\u9ece\u660e\u7834\u6653\u524d", "director": ["\u7406\u67e5\u5fb7\u00b7\u6797\u514b\u83b1\u7279 Richard Linklater"], "date": "1995", "region": ["\u7f8e\u56fd", "\u5965\u5730\u5229", "\u745e\u58eb"], "genre": ["\u5267\u60c5", "\u7231\u60c5"]}, {"index": 111, "title": "\u4eba\u751f\u679c\u5b9e", "director": ["\u4f0f\u539f\u5065\u4e4b Kenshi Fushihara"], "date": "2017", "region": ["\u65e5\u672c"], "genre": ["\u7eaa\u5f55\u7247"]}, {"index": 112, "title": "\u4e00\u4e00", "director": ["\u6768\u5fb7\u660c Edward Yang"], "date": "2000", "region": ["\u4e2d\u56fd\u53f0\u6e7e", "\u65e5\u672c"], "genre": ["\u5267\u60c5", "\u7231\u60c5", "\u5bb6\u5ead"]}, {"index": 113, "title": "\u8759\u8760\u4fa0\uff1a\u9ed1\u6697\u9a91\u58eb\u5d1b\u8d77", "director": ["\u514b\u91cc\u65af\u6258\u5f17\u00b7\u8bfa\u5170 Christopher Nolan"], "date": "2012", "region": ["\u7f8e\u56fd", "\u82f1\u56fd"], "genre": ["\u5267\u60c5", "\u52a8\u4f5c", "\u79d1\u5e7b", "\u72af\u7f6a", "\u60ca\u609a"]}, {"index": 114, "title": "\u5c0f\u68ee\u6797 \u51ac\u6625\u7bc7", "director": ["\u68ee\u6df3\u4e00 Junichi Mori"], "date": "2015", "region": ["\u65e5\u672c"], "genre": ["\u5267\u60c5"]}, {"index": 115, "title": "\u83ca\u6b21\u90ce\u7684\u590f\u5929", "director": ["\u5317\u91ce\u6b66 Takeshi Kitano"], "date": "1999", "region": ["\u65e5\u672c"], "genre": ["\u5267\u60c5", "\u559c\u5267"]}, {"index": 116, "title": "\u6d88\u5931\u7684\u7231\u4eba", "director": ["\u5927\u536b\u00b7\u82ac\u5947 David Fincher"], "date": "2014", "region": ["\u7f8e\u56fd"], "genre": ["\u5267\u60c5", "\u72af\u7f6a", "\u60ac\u7591", "\u60ca\u609a"]}, {"index": 117, "title": "\u5165\u6b93\u5e08", "director": ["\u6cf7\u7530\u6d0b\u4e8c\u90ce Y\u00f4jir\u00f4 Takita"], "date": "2008", "region": ["\u65e5\u672c"], "genre": ["\u5267\u60c5"]}, {"index": 118, "title": "\u65e0\u4eba\u77e5\u6653", "director": ["\u662f\u679d\u88d5\u548c Hirokazu Koreeda"], "date": "2004", "region": ["\u65e5\u672c"], "genre": ["\u5267\u60c5"]}, {"index": 119, "title": "\u54c8\u5229\u00b7\u6ce2\u7279\u4e0e\u963f\u5179\u5361\u73ed\u7684\u56da\u5f92", "director": ["Alfonso Cuar\u00f3n"], "date": "2004", "region": ["\u82f1\u56fd", "\u7f8e\u56fd"], "genre": ["\u5947\u5e7b", "\u5192\u9669"]}, {"index": 120, "title": "\u8d85\u80fd\u9646\u6218\u961f", "director": ["\u5510\u00b7\u970d\u5c14 Don Hall", "\u514b\u91cc\u65af\u00b7\u5a01\u5ec9\u59c6\u65af Chris Williams"], "date": "2014", "region": ["\u7f8e\u56fd"], "genre": ["\u559c\u5267", "\u52a8\u4f5c", "\u79d1\u5e7b", "\u52a8\u753b", "\u5192\u9669"]}, {"index": 121, "title": "\u5029\u5973\u5e7d\u9b42", "director": ["\u7a0b\u5c0f\u4e1c Siu-Tung Ching"], "date": "1987", "region": ["\u4e2d\u56fd\u9999\u6e2f"], "genre": ["\u7231\u60c5", "\u5947\u5e7b", "\u6b66\u4fa0", "\u53e4\u88c5"]}, {"index": 122, "title": "\u4fa7\u8033\u503e\u542c", "director": ["\u8fd1\u85e4\u559c\u6587 Yoshifumi Kondo"], "date": "1995", "region": ["\u65e5\u672c"], "genre": ["\u5267\u60c5", "\u7231\u60c5", "\u52a8\u753b"]}, {"index": 123, "title": "\u5b8c\u7f8e\u7684\u4e16\u754c", "director": ["\u514b\u6797\u7279\u00b7\u4f0a\u65af\u7279\u4f0d\u5fb7 Clint Eastwood"], "date": "1993", "region": ["\u7f8e\u56fd"], "genre": ["\u5267\u60c5", "\u72af\u7f6a"]}, {"index": 124, "title": "\u501f\u4e1c\u897f\u7684\u5c0f\u4eba\u963f\u8389\u57c3\u8482", "director": ["\u7c73\u6797\u5b8f\u660c Hiromasa Yonebayashi"], "date": "2010", "region": ["\u65e5\u672c"], "genre": ["\u52a8\u753b", "\u5947\u5e7b", "\u5192\u9669"]}, {"index": 125, "title": "\u751c\u871c\u871c", "director": ["\u9648\u53ef\u8f9b Peter Chan"], "date": "1996", "region": ["\u4e2d\u56fd\u9999\u6e2f"], "genre": ["\u5267\u60c5", "\u7231\u60c5"]}, {"index": 126, "title": "\u7231\u5728\u65e5\u843d\u9ec4\u660f\u65f6", "director": ["\u7406\u67e5\u5fb7\u00b7\u6797\u514b\u83b1\u7279 Richard Linklater"], "date": "2004", "region": ["\u7f8e\u56fd", "\u6cd5\u56fd"], "genre": ["\u5267\u60c5", "\u7231\u60c5"]}, {"index": 127, "title": "\u8424\u706b\u4e4b\u68ee", "director": ["\u5927\u68ee\u8d35\u5f18 Takahiro Omori"], "date": "2011", "region": ["\u65e5\u672c"], "genre": ["\u5267\u60c5", "\u7231\u60c5", "\u52a8\u753b", "\u5947\u5e7b"]}, {"index": 128, "title": "\u9a6f\u9f99\u9ad8\u624b", "director": ["\u8fea\u6069\u00b7\u5fb7\u5e03\u6d1b\u65af Dean DeBlois", "\u514b\u91cc\u65af\u00b7\u6851\u5fb7\u65af Chris Sanders"], "date": "2010", "region": ["\u7f8e\u56fd"], "genre": ["\u52a8\u753b", "\u5947\u5e7b", "\u5192\u9669"]}, {"index": 129, "title": "\u739b\u4e3d\u548c\u9a6c\u514b\u601d", "director": ["\u4e9a\u5f53\u00b7\u827e\u7565\u7279 Adam Elliot"], "date": "2009", "region": ["\u6fb3\u5927\u5229\u4e9a", "\u7f8e\u56fd"], "genre": ["\u5267\u60c5", "\u559c\u5267", "\u52a8\u753b"]}, {"index": 130, "title": "\u5e78\u798f\u7ec8\u70b9\u7ad9", "director": ["\u53f2\u8482\u6587\u00b7\u65af\u76ae\u5c14\u4f2f\u683c Steven Spielberg"], "date": "2004", "region": ["\u7f8e\u56fd"], "genre": ["\u559c\u5267", "\u5267\u60c5", "\u7231\u60c5"]}, {"index": 131, "title": "\u5929\u4e66\u5947\u8c2d", "director": ["\u738b\u6811\u5ff1 Shuchen Wang", "\u94b1\u8fd0\u8fbe Yunda Qian"], "date": "1983(\u4e2d\u56fd\u5927\u9646)", "region": ["\u4e2d\u56fd\u5927\u9646"], "genre": ["\u52a8\u753b", "\u5947\u5e7b"]}, {"index": 132, "title": "\u544a\u767d", "director": ["\u4e2d\u5c9b\u54f2\u4e5f Tetsuya Nakashima"], "date": "2010", "region": ["\u65e5\u672c"], "genre": ["\u5267\u60c5", "\u60ac\u7591"]}, {"index": 133, "title": "\u5927\u9c7c", "director": ["\u8482\u59c6\u00b7\u6ce2\u987f Tim Burton"], "date": "2003", "region": ["\u7f8e\u56fd"], "genre": ["\u5267\u60c5", "\u5bb6\u5ead", "\u5947\u5e7b", "\u5192\u9669"]}, {"index": 134, "title": "\u9633\u5149\u59d0\u59b9\u6dd8", "director": ["\u59dc\u70af\u54f2 Hyeong-Cheol Kang"], "date": "2011", "region": ["\u97e9\u56fd"], "genre": ["\u5267\u60c5", "\u559c\u5267"]}, {"index": 135, "title": "\u54c8\u5229\u00b7\u6ce2\u7279\u4e0e\u5bc6\u5ba4", "director": ["Chris Columbus"], "date": "2002", "region": ["\u7f8e\u56fd", "\u82f1\u56fd", "\u5fb7\u56fd"], "genre": ["\u5947\u5e7b", "\u5192\u9669"]}, {"index": 136, "title": "\u5c04\u96d5\u82f1\u96c4\u4f20\u4e4b\u4e1c\u6210\u897f\u5c31", "director": ["\u5218\u9547\u4f1f Jeffrey Lau"], "date": "1993", "region": ["\u4e2d\u56fd\u9999\u6e2f"], "genre": ["\u559c\u5267", "\u5947\u5e7b", "\u6b66\u4fa0", "\u53e4\u88c5"]}, {"index": 137, "title": "\u602a\u517d\u7535\u529b\u516c\u53f8", "director": ["\u5f7c\u7279\u00b7\u9053\u683c\u7279 Pete Docter", "\u5927\u536b\u00b7\u65af\u6c83\u66fc David Silverman"], "date": "2001", "region": ["\u7f8e\u56fd"], "genre": ["\u513f\u7ae5", "\u559c\u5267", "\u52a8\u753b", "\u5947\u5e7b", "\u5192\u9669"]}, {"index": 138, "title": "\u6050\u6016\u76f4\u64ad", "director": ["\u91d1\u79c9\u7950 Byeong-woo Kim"], "date": "2013", "region": ["\u97e9\u56fd"], "genre": ["\u5267\u60c5", "\u72af\u7f6a", "\u60ac\u7591"]}, {"index": 139, "title": "\u795e\u5077\u5976\u7238", "director": ["\u76ae\u827e\u5c14\u00b7\u67ef\u82ac Pierre Coffin", "\u514b\u91cc\u65af\u00b7\u96f7\u7eb3\u5fb7 Chris Renaud"], "date": "2010", "region": ["\u7f8e\u56fd", "\u6cd5\u56fd"], "genre": ["\u559c\u5267", "\u52a8\u753b", "\u5192\u9669"]}, {"index": 140, "title": "\u65f6\u7a7a\u604b\u65c5\u4eba", "director": ["\u7406\u67e5\u5fb7\u00b7\u67ef\u8482\u65af Richard Curtis"], "date": "2013", "region": ["\u82f1\u56fd"], "genre": ["\u559c\u5267", "\u7231\u60c5", "\u5947\u5e7b"]}, {"index": 141, "title": "\u73a9\u5177\u603b\u52a8\u54583", "director": ["\u674e\u00b7\u6602\u514b\u91cc\u5947 Lee Unkrich"], "date": "2010", "region": ["\u7f8e\u56fd"], "genre": ["\u559c\u5267", "\u52a8\u753b", "\u5947\u5e7b", "\u5192\u9669"]}, {"index": 142, "title": "\u50b2\u6162\u4e0e\u504f\u89c1", "director": ["\u4e54\u00b7\u6000\u7279 Joe Wright"], "date": "2005", "region": ["\u6cd5\u56fd", "\u82f1\u56fd", "\u7f8e\u56fd"], "genre": ["\u5267\u60c5", "\u7231\u60c5"]}, {"index": 143, "title": "\u6559\u72363", "director": ["\u5f17\u6717\u897f\u65af\u00b7\u798f\u7279\u00b7\u79d1\u6ce2\u62c9 Francis Ford Coppola"], "date": "1990", "region": ["\u7f8e\u56fd"], "genre": ["\u5267\u60c5", "\u72af\u7f6a"]}, {"index": 144, "title": "\u91dc\u5c71\u884c", "director": ["\u5ef6\u5c1a\u660a Sang-ho Yeon"], "date": "2016", "region": ["\u97e9\u56fd"], "genre": ["\u52a8\u4f5c", "\u60ca\u609a", "\u707e\u96be"]}, {"index": 145, "title": "\u54ea\u5412\u95f9\u6d77", "director": ["\u4e25\u5b9a\u5baa Dingxian Yan", "\u738b\u6811\u5ff1 Shuchen Wang"], "date": "1979", "region": ["\u4e2d\u56fd\u5927\u9646"], "genre": ["\u5192\u9669", "\u52a8\u753b", "\u5947\u5e7b"]}, {"index": 146, "title": "\u8840\u6218\u94a2\u952f\u5cad", "director": ["\u6885\u5c14\u00b7\u5409\u5e03\u68ee Mel Gibson"], "date": "2016", "region": ["\u6fb3\u5927\u5229\u4e9a", "\u7f8e\u56fd"], "genre": ["\u5267\u60c5", "\u4f20\u8bb0", "\u5386\u53f2", "\u6218\u4e89"]}, {"index": 147, "title": "\u4e00\u4e2a\u53eb\u6b27\u7ef4\u7684\u7537\u4eba\u51b3\u5b9a\u53bb\u6b7b", "director": ["\u6c49\u5185\u65af\u00b7\u8d6b\u5c14\u59c6 Hannes Holm"], "date": "2015", "region": ["\u745e\u5178"], "genre": ["\u5267\u60c5"]}, {"index": 148, "title": "\u88ab\u89e3\u6551\u7684\u59dc\u6208", "director": ["\u6606\u6c40\u00b7\u5854\u4f26\u8482\u8bfa Quentin Tarantino"], "date": "2012", "region": ["\u7f8e\u56fd"], "genre": ["\u5267\u60c5", "\u52a8\u4f5c", "\u897f\u90e8", "\u5192\u9669"]}, {"index": 149, "title": "\u4e03\u6b66\u58eb", "director": ["\u9ed1\u6cfd\u660e Akira Kurosawa"], "date": "1954", "region": ["\u65e5\u672c"], "genre": ["\u52a8\u4f5c", "\u5192\u9669", "\u5267\u60c5"]}, {"index": 150, "title": "\u672a\u9ebb\u7684\u90e8\u5c4b", "director": ["\u4eca\u654f Satoshi Kon"], "date": "1997", "region": ["\u65e5\u672c"], "genre": ["\u52a8\u753b", "\u5947\u5e7b", "\u60ca\u609a"]}, {"index": 151, "title": "\u559c\u5bb4", "director": ["\u674e\u5b89 Ang Lee"], "date": "1993", "region": ["\u4e2d\u56fd\u53f0\u6e7e", "\u7f8e\u56fd"], "genre": ["\u5267\u60c5", "\u559c\u5267", "\u7231\u60c5", "\u540c\u6027", "\u5bb6\u5ead"]}, {"index": 152, "title": "\u5934\u53f7\u73a9\u5bb6", "director": ["\u53f2\u8482\u6587\u00b7\u65af\u76ae\u5c14\u4f2f\u683c Steven Spielberg"], "date": "2018", "region": ["\u7f8e\u56fd"], "genre": ["\u52a8\u4f5c", "\u79d1\u5e7b", "\u5192\u9669"]}, {"index": 153, "title": "\u7535\u952f\u60ca\u9b42", "director": ["\u8a79\u59c6\u65af\u00b7\u6e29 James Wan"], "date": "2004", "region": ["\u7f8e\u56fd"], "genre": ["\u60ac\u7591", "\u60ca\u609a", "\u6050\u6016"]}, {"index": 154, "title": "\u6211\u662f\u5c71\u59c6", "director": ["\u6770\u831c\u00b7\u5c3c\u5c14\u68ee Jessie Nelson"], "date": "2001", "region": ["\u7f8e\u56fd"], "genre": ["\u5267\u60c5", "\u5bb6\u5ead"]}, {"index": 155, "title": "\u98ce\u4e4b\u8c37", "director": ["\u5bab\u5d0e\u9a8f Hayao Miyazaki"], "date": "1984", "region": ["\u65e5\u672c"], "genre": ["\u52a8\u753b", "\u5947\u5e7b", "\u5192\u9669"]}, {"index": 156, "title": "\u4e0a\u5e1d\u4e4b\u57ce", "director": ["\u8d39\u5c14\u5357\u591a\u00b7\u6885\u91cc\u5c14\u65af Fernando Meirelles", "\u5361\u8fea\u4e9a\u00b7\u5170\u5fb7 K\u00e1tia Lund"], "date": "2002", "region": ["\u5df4\u897f", "\u6cd5\u56fd"], "genre": ["\u72af\u7f6a", "\u5267\u60c5"]}, {"index": 157, "title": "\u82f1\u96c4\u672c\u8272", "director": ["\u5434\u5b87\u68ee John Woo"], "date": "1986", "region": ["\u4e2d\u56fd\u9999\u6e2f"], "genre": ["\u5267\u60c5", "\u52a8\u4f5c", "\u72af\u7f6a"]}, {"index": 158, "title": "\u5362\u65fa\u8fbe\u996d\u5e97", "director": ["\u7279\u745e\u00b7\u4e54\u6cbb Terry George"], "date": "2004", "region": ["\u82f1\u56fd", "\u5357\u975e", "\u610f\u5927\u5229"], "genre": ["\u5267\u60c5", "\u4f20\u8bb0", "\u5386\u53f2", "\u6218\u4e89"]}, {"index": 159, "title": "\u75af\u72c2\u539f\u59cb\u4eba", "director": ["\u79d1\u514b\u00b7\u5fb7\u00b7\u7c73\u79d1 Kirk De Micco", "\u514b\u91cc\u65af\u00b7\u6851\u5fb7\u65af Chris Sanders"], "date": "2013", "region": ["\u7f8e\u56fd"], "genre": ["\u559c\u5267", "\u52a8\u753b", "\u5192\u9669"]}, {"index": 160, "title": "\u8c0d\u5f71\u91cd\u91cd3", "director": ["\u4fdd\u7f57\u00b7\u683c\u6797\u683c\u62c9\u65af Paul Greengrass"], "date": "2007", "region": ["\u7f8e\u56fd", "\u5fb7\u56fd"], "genre": ["\u52a8\u4f5c", "\u60ac\u7591", "\u60ca\u609a"]}, {"index": 161, "title": "\u4e09\u5757\u5e7f\u544a\u724c", "director": ["\u9a6c\u4e01\u00b7\u9ea6\u514b\u5510\u7eb3 Martin McDonagh"], "date": "2017", "region": ["\u7f8e\u56fd", "\u82f1\u56fd"], "genre": ["\u5267\u60c5", "\u72af\u7f6a"]}, {"index": 162, "title": "\u65b0\u4e16\u754c", "director": ["\u6734\u52cb\u653f Hoon-jung Park"], "date": "2013", "region": ["\u97e9\u56fd"], "genre": ["\u5267\u60c5", "\u72af\u7f6a"]}, {"index": 163, "title": "\u82b1\u6837\u5e74\u534e", "director": ["\u738b\u5bb6\u536b Kar Wai Wong"], "date": "2000", "region": ["\u4e2d\u56fd\u9999\u6e2f"], "genre": ["\u5267\u60c5", "\u7231\u60c5"]}, {"index": 164, "title": "\u6a21\u4eff\u6e38\u620f", "director": ["\u83ab\u6ed5\u00b7\u6cf0\u675c\u59c6 Morten Tyldum"], "date": "2014", "region": ["\u82f1\u56fd", "\u7f8e\u56fd"], "genre": ["\u5267\u60c5", "\u4f20\u8bb0", "\u6218\u4e89", "\u540c\u6027"]}, {"index": 165, "title": "\u7eb5\u6a2a\u56db\u6d77", "director": ["\u5434\u5b87\u68ee John Woo"], "date": "1991", "region": ["\u4e2d\u56fd\u9999\u6e2f"], "genre": ["\u5267\u60c5", "\u559c\u5267", "\u52a8\u4f5c", "\u72af\u7f6a"]}, {"index": 166, "title": "\u9ed1\u5ba2\u5e1d\u56fd3\uff1a\u77e9\u9635\u9769\u547d", "director": ["\u62c9\u5a1c\u00b7\u6c83\u5353\u65af\u57fa Lana Wachowski", "\u8389\u8389\u00b7\u6c83\u5353\u65af\u57fa Lilly Wachowski"], "date": "2003", "region": ["\u7f8e\u56fd"], "genre": ["\u52a8\u4f5c", "\u79d1\u5e7b"]}, {"index": 167, "title": "\u8fbe\u62c9\u65af\u4e70\u5bb6\u4ff1\u4e50\u90e8", "director": ["\u8ba9-\u9a6c\u514b\u00b7\u74e6\u96f7 Jean-Marc Vall\u00e9e"], "date": "2013", "region": ["\u7f8e\u56fd"], "genre": ["\u5267\u60c5", "\u4f20\u8bb0", "\u540c\u6027"]}, {"index": 168, "title": "\u5c81\u6708\u795e\u5077", "director": ["\u7f57\u542f\u9510 Alex Law"], "date": "2010", "region": ["\u4e2d\u56fd\u9999\u6e2f", "\u4e2d\u56fd\u5927\u9646"], "genre": ["\u5267\u60c5", "\u5bb6\u5ead"]}, {"index": 169, "title": "\u5934\u8111\u7279\u5de5\u961f", "director": ["\u5f7c\u7279\u00b7\u9053\u683c\u7279 Pete Docter", "\u7f57\u7eb3\u5c14\u591a\u00b7\u5fb7\u5c14\u00b7\u5361\u95e8 Ronaldo Del Carmen"], "date": "2015", "region": ["\u7f8e\u56fd"], "genre": ["\u559c\u5267", "\u52a8\u753b", "\u5192\u9669"]}, {"index": 170, "title": "\u5fc3\u8ff7\u5bab", "director": ["\u5ffb\u94b0\u5764 Yukun Xin"], "date": "2014", "region": ["\u4e2d\u56fd\u5927\u9646"], "genre": ["\u5267\u60c5", "\u72af\u7f6a", "\u60ac\u7591"]}, {"index": 171, "title": "\u4f60\u7684\u540d\u5b57\u3002", "director": ["\u65b0\u6d77\u8bda Makoto Shinkai"], "date": "2016", "region": ["\u65e5\u672c"], "genre": ["\u5267\u60c5", "\u7231\u60c5", "\u52a8\u753b"]}, {"index": 172, "title": "\u8bb0\u5fc6\u788e\u7247", "director": ["\u514b\u91cc\u65af\u6258\u5f17\u00b7\u8bfa\u5170 Christopher Nolan"], "date": "2000", "region": ["\u7f8e\u56fd"], "genre": ["\u72af\u7f6a", "\u5267\u60c5", "\u60ac\u7591", "\u60ca\u609a"]}, {"index": 173, "title": "\u5bc4\u751f\u866b", "director": ["\u5949\u4fca\u660a Joon-ho Bong"], "date": "2019", "region": ["\u97e9\u56fd"], "genre": ["\u5267\u60c5", "\u559c\u5267"]}, {"index": 174, "title": "\u5fe0\u72ac\u516b\u516c\u7269\u8bed", "director": ["Seijir\u00f4 K\u00f4yama"], "date": "1987", "region": ["\u65e5\u672c"], "genre": ["\u5267\u60c5"]}, {"index": 175, "title": "\u8352\u86ee\u6545\u4e8b", "director": ["\u8fbe\u7c73\u5b89\u00b7\u65af\u5179\u5f17\u9686 Dami\u00e1n Szifron"], "date": "2014", "region": ["\u963f\u6839\u5ef7", "\u897f\u73ed\u7259"], "genre": ["\u5267\u60c5", "\u559c\u5267", "\u72af\u7f6a"]}, {"index": 176, "title": "\u6d77\u8857\u65e5\u8bb0", "director": ["\u662f\u679d\u88d5\u548c Hirokazu Koreeda"], "date": "2015", "region": ["\u65e5\u672c"], "genre": ["\u5267\u60c5", "\u5bb6\u5ead"]}, {"index": 177, "title": "\u7206\u88c2\u9f13\u624b", "director": ["\u8fbe\u7c73\u6069\u00b7\u67e5\u6cfd\u96f7 Damien Chazelle"], "date": "2014", "region": ["\u7f8e\u56fd"], "genre": ["\u5267\u60c5", "\u97f3\u4e50"]}, {"index": 178, "title": "\u771f\u7231\u81f3\u4e0a", "director": ["\u7406\u67e5\u5fb7\u00b7\u67ef\u8482\u65af Richard Curtis"], "date": "2003", "region": ["\u82f1\u56fd", "\u7f8e\u56fd", "\u6cd5\u56fd"], "genre": ["\u559c\u5267", "\u5267\u60c5", "\u7231\u60c5"]}, {"index": 179, "title": "\u8d2b\u6c11\u7a9f\u7684\u767e\u4e07\u5bcc\u7fc1", "director": ["\u4e39\u5c3c\u00b7\u9c8d\u5c14 Danny Boyle", "\u6d1b\u8299\u7433\u00b7\u5766\u4e39 Loveleen Tandan"], "date": "2008", "region": ["\u82f1\u56fd"], "genre": ["\u5267\u60c5", "\u7231\u60c5"]}, {"index": 180, "title": "\u60ca\u9b42\u8bb0", "director": ["\u963f\u5c14\u5f17\u96f7\u5fb7\u00b7\u5e0c\u533a\u67ef\u514b Alfred Hitchcock"], "date": "1960", "region": ["\u7f8e\u56fd"], "genre": ["\u60ac\u7591", "\u60ca\u609a", "\u6050\u6016"]}, {"index": 181, "title": "\u4e1c\u90aa\u897f\u6bd2", "director": ["\u738b\u5bb6\u536b Kar Wai Wong"], "date": "1994", "region": ["\u4e2d\u56fd\u9999\u6e2f", "\u4e2d\u56fd\u53f0\u6e7e"], "genre": ["\u5267\u60c5", "\u52a8\u4f5c", "\u7231\u60c5", "\u6b66\u4fa0", "\u53e4\u88c5"]}, {"index": 182, "title": "\u54c8\u5229\u00b7\u6ce2\u7279\u4e0e\u706b\u7130\u676f", "director": ["\u8fc8\u514b\u00b7\u5185\u5a01\u5c14 Mike Newell"], "date": "2005", "region": ["\u82f1\u56fd", "\u7f8e\u56fd"], "genre": ["\u60ac\u7591", "\u5947\u5e7b", "\u5192\u9669"]}, {"index": 183, "title": "\u8424\u706b\u866b\u4e4b\u5893", "director": ["\u9ad8\u7551\u52cb Isao Takahata"], "date": "1988", "region": ["\u65e5\u672c"], "genre": ["\u52a8\u753b", "\u5267\u60c5", "\u6218\u4e89"]}, {"index": 184, "title": "\u9ed1\u5929\u9e45", "director": ["\u8fbe\u4f26\u00b7\u963f\u7f57\u8bfa\u592b\u65af\u57fa Darren Aronofsky"], "date": "2010", "region": ["\u7f8e\u56fd"], "genre": ["\u5267\u60c5", "\u60ca\u609a"]}, {"index": 185, "title": "\u5c0f\u5077\u5bb6\u65cf", "director": ["\u662f\u679d\u88d5\u548c Hirokazu Koreeda"], "date": "2018", "region": ["\u65e5\u672c"], "genre": ["\u5267\u60c5", "\u72af\u7f6a", "\u5bb6\u5ead"]}, {"index": 186, "title": "\u7eff\u91cc\u5947\u8ff9", "director": ["Frank Darabont"], "date": "1999", "region": ["\u7f8e\u56fd"], "genre": ["\u72af\u7f6a", "\u5267\u60c5", "\u5947\u5e7b", "\u60ac\u7591"]}, {"index": 187, "title": "\u65e0\u654c\u7834\u574f\u738b", "director": ["\u745e\u5947\u00b7\u83ab\u5c14 Rich Moore"], "date": "2012", "region": ["\u7f8e\u56fd"], "genre": ["\u559c\u5267", "\u52a8\u753b", "\u5947\u5e7b", "\u5192\u9669"]}, {"index": 188, "title": "\u4f60\u770b\u8d77\u6765\u597d\u50cf\u5f88\u597d\u5403", "director": ["\u85e4\u68ee\u96c5\u4e5f Masaya Fujimori"], "date": "2010", "region": ["\u65e5\u672c"], "genre": ["\u5267\u60c5", "\u52a8\u753b", "\u513f\u7ae5"]}, {"index": 189, "title": "\u51b0\u5ddd\u65f6\u4ee3", "director": ["\u5361\u6d1b\u65af\u00b7\u6c99\u5c14\u4e39\u54c8 Carlos Saldanha", "\u514b\u91cc\u65af\u00b7\u97e6\u5947 Chris Wedge"], "date": "2002", "region": ["\u7f8e\u56fd"], "genre": ["\u559c\u5267", "\u52a8\u753b", "\u5192\u9669"]}, {"index": 190, "title": "\u7231\u5728\u5348\u591c\u964d\u4e34\u524d", "director": ["\u7406\u67e5\u5fb7\u00b7\u6797\u514b\u83b1\u7279 Richard Linklater"], "date": "2013", "region": ["\u7f8e\u56fd", "\u5e0c\u814a"], "genre": ["\u5267\u60c5", "\u7231\u60c5"]}, {"index": 191, "title": "\u4e5d\u54c1\u829d\u9ebb\u5b98", "director": ["\u738b\u6676 Jing Wong"], "date": "1994", "region": ["\u4e2d\u56fd\u9999\u6e2f", "\u4e2d\u56fd\u5927\u9646"], "genre": ["\u5267\u60c5", "\u559c\u5267", "\u53e4\u88c5"]}, {"index": 192, "title": "\u96e8\u4eba", "director": ["\u5df4\u745e\u00b7\u83b1\u6587\u68ee Barry Levinson"], "date": "1988", "region": ["\u7f8e\u56fd"], "genre": ["\u5267\u60c5"]}, {"index": 193, "title": "\u75af\u72c2\u7684\u77f3\u5934", "director": ["\u5b81\u6d69 Hao Ning"], "date": "2006", "region": ["\u4e2d\u56fd\u5927\u9646", "\u4e2d\u56fd\u9999\u6e2f"], "genre": ["\u559c\u5267", "\u72af\u7f6a"]}, {"index": 194, "title": "\u604b\u604b\u7b14\u8bb0\u672c", "director": ["\u5c3c\u514b\u00b7\u5361\u7d22\u7ef4\u8328 Nick Cassavetes"], "date": "2004", "region": ["\u7f8e\u56fd"], "genre": ["\u5267\u60c5", "\u7231\u60c5"]}, {"index": 195, "title": "\u6050\u6016\u6e38\u8f6e", "director": ["\u514b\u91cc\u65af\u6258\u5f17\u00b7\u53f2\u5bc6\u65af Christopher Smith"], "date": "2009", "region": ["\u82f1\u56fd", "\u6fb3\u5927\u5229\u4e9a"], "genre": ["\u5267\u60c5", "\u60ac\u7591", "\u60ca\u609a"]}, {"index": 196, "title": "\u96e8\u4e2d\u66f2", "director": ["\u65af\u5766\u5229\u00b7\u591a\u5357 Stanley Donen", "\u5409\u6069\u00b7\u51ef\u5229 Gene Kelly"], "date": "1952", "region": ["\u7f8e\u56fd"], "genre": ["\u559c\u5267", "\u6b4c\u821e", "\u7231\u60c5"]}, {"index": 197, "title": "\u9b54\u5973\u5b85\u6025\u4fbf", "director": ["\u5bab\u5d0e\u9a8f Hayao Miyazaki"], "date": "1989", "region": ["\u65e5\u672c"], "genre": ["\u52a8\u753b", "\u5947\u5e7b", "\u5192\u9669"]}, {"index": 198, "title": "\u5947\u8ff9\u7537\u5b69", "director": ["\u65af\u8482\u82ac\u00b7\u5353\u535a\u65af\u57fa Stephen Chbosky"], "date": "2017", "region": ["\u7f8e\u56fd", "\u4e2d\u56fd\u9999\u6e2f"], "genre": ["\u5267\u60c5", "\u513f\u7ae5", "\u5bb6\u5ead"]}, {"index": 199, "title": "\u8272\uff0c\u6212", "director": ["\u674e\u5b89 Ang Lee"], "date": "2007", "region": ["\u4e2d\u56fd\u53f0\u6e7e", "\u4e2d\u56fd\u5927\u9646", "\u7f8e\u56fd", "\u4e2d\u56fd\u9999\u6e2f"], "genre": ["\u5267\u60c5", "\u7231\u60c5", "\u60c5\u8272"]}, {"index": 200, "title": "2001\u592a\u7a7a\u6f2b\u6e38", "director": ["\u65af\u5766\u5229\u00b7\u5e93\u5e03\u91cc\u514b Stanley Kubrick"], "date": "1968", "region": ["\u82f1\u56fd", "\u7f8e\u56fd"], "genre": ["\u79d1\u5e7b", "\u60ca\u609a", "\u5192\u9669"]}, {"index": 201, "title": "\u864e\u53e3\u8131\u9669", "director": ["\u6770\u62c9\u5c14\u00b7\u4e4c\u91cc G\u00e9rard Oury"], "date": "1966", "region": ["\u6cd5\u56fd", "\u82f1\u56fd"], "genre": ["\u559c\u5267", "\u6218\u4e89"]}, {"index": 202, "title": "\u6d77\u8fb9\u7684\u66fc\u5f7b\u65af\u7279", "director": ["\u80af\u5c3c\u65af\u00b7\u7f57\u7eb3\u6839 Kenneth Lonergan"], "date": "2016", "region": ["\u7f8e\u56fd"], "genre": ["\u5267\u60c5", "\u5bb6\u5ead"]}, {"index": 203, "title": "\u4eba\u5de5\u667a\u80fd", "director": ["\u53f2\u8482\u6587\u00b7\u65af\u76ae\u5c14\u4f2f\u683c Steven Spielberg"], "date": "2001", "region": ["\u7f8e\u56fd", "\u82f1\u56fd"], "genre": ["\u5267\u60c5", "\u79d1\u5e7b"]}, {"index": 204, "title": "\u53ef\u53ef\u897f\u91cc", "director": ["\u9646\u5ddd Chuan Lu"], "date": "2004", "region": ["\u4e2d\u56fd\u5927\u9646", "\u4e2d\u56fd\u9999\u6e2f"], "genre": ["\u5267\u60c5", "\u72af\u7f6a"]}, {"index": 205, "title": "\u57ce\u5e02\u4e4b\u5149", "director": ["Charles Chaplin"], "date": "1931", "region": ["\u7f8e\u56fd"], "genre": ["\u559c\u5267", "\u5267\u60c5", "\u7231\u60c5"]}, {"index": 206, "title": "\u623f\u95f4", "director": ["\u4f26\u5c3c\u00b7\u963f\u4f2f\u62c9\u7f55\u68ee Lenny Abrahamson"], "date": "2015", "region": ["\u7231\u5c14\u5170", "\u52a0\u62ff\u5927", "\u82f1\u56fd", "\u7f8e\u56fd"], "genre": ["\u5267\u60c5", "\u5bb6\u5ead"]}, {"index": 207, "title": "\u4e8c\u5341\u4e8c", "director": ["\u90ed\u67ef Ke Guo"], "date": "2015", "region": ["\u4e2d\u56fd\u5927\u9646"], "genre": ["\u7eaa\u5f55\u7247"]}, {"index": 208, "title": "\u7f57\u751f\u95e8", "director": ["\u9ed1\u6cfd\u660e Akira Kurosawa"], "date": "1950", "region": ["\u65e5\u672c"], "genre": ["\u5267\u60c5", "\u72af\u7f6a", "\u60ac\u7591"]}, {"index": 209, "title": "\u521d\u604b\u8fd9\u4ef6\u5c0f\u4e8b", "director": ["\u666e\u7279\u9e4f\u00b7\u666e\u7f57\u8428\u5361\u00b7\u90a3\u00b7\u8428\u514b\u90a3\u5361\u6797 Puttipong Promsaka Na Sakolnakorn", "\u534e\u68ee\u00b7\u6ce2\u514b\u5f6d...<br>\n                            2010"], "date": "2010", "region": ["\u6cf0\u56fd"], "genre": ["\u5267\u60c5", "\u559c\u5267", "\u7231\u60c5"]}, {"index": 210, "title": "\u7ec8\u7ed3\u80052\uff1a\u5ba1\u5224\u65e5", "director": ["\u8a79\u59c6\u65af\u00b7\u5361\u6885\u9686 James Cameron"], "date": "1991", "region": ["\u7f8e\u56fd", "\u6cd5\u56fd"], "genre": ["\u52a8\u4f5c", "\u79d1\u5e7b"]}, {"index": 211, "title": "\u5927\u4f5b\u666e\u62c9\u65af", "director": ["\u9ec4\u4fe1\u5c27 Hsin-yao Huang"], "date": "2017", "region": ["\u4e2d\u56fd\u53f0\u6e7e"], "genre": ["\u5267\u60c5", "\u559c\u5267"]}, {"index": 212, "title": "\u9057\u613f\u6e05\u5355", "director": ["\u7f57\u4f2f\u00b7\u83b1\u7eb3 Rob Reiner"], "date": "2007", "region": ["\u7f8e\u56fd"], "genre": ["\u5192\u9669", "\u559c\u5267", "\u5267\u60c5"]}, {"index": 213, "title": "\u726f\u5cad\u8857\u5c11\u5e74\u6740\u4eba\u4e8b\u4ef6", "director": ["\u6768\u5fb7\u660c Edward Yang"], "date": "1991", "region": ["\u4e2d\u56fd\u53f0\u6e7e"], "genre": ["\u5267\u60c5", "\u72af\u7f6a"]}, {"index": 214, "title": "\u6ce2\u897f\u7c73\u4e9a\u72c2\u60f3\u66f2", "director": ["\u5e03\u83b1\u6069\u00b7\u8f9b\u683c Bryan Singer"], "date": "2018", "region": ["\u82f1\u56fd", "\u7f8e\u56fd"], "genre": ["\u5267\u60c5", "\u4f20\u8bb0", "\u540c\u6027", "\u97f3\u4e50"]}, {"index": 215, "title": "\u6e90\u4ee3\u7801", "director": ["\u9093\u80af\u00b7\u743c\u65af Duncan Jones"], "date": "2011", "region": ["\u7f8e\u56fd", "\u52a0\u62ff\u5927"], "genre": ["\u79d1\u5e7b", "\u60ac\u7591", "\u60ca\u609a"]}, {"index": 216, "title": "\u9b42\u65ad\u84dd\u6865", "director": ["\u8302\u6587\u00b7\u52d2\u9c81\u74e6 Mervyn LeRoy"], "date": "1940", "region": ["\u7f8e\u56fd"], "genre": ["\u5267\u60c5", "\u7231\u60c5", "\u6218\u4e89"]}, {"index": 217, "title": "\u65b0\u9f99\u95e8\u5ba2\u6808", "director": ["\u674e\u60e0\u6c11 Raymond Lee"], "date": "1992", "region": ["\u4e2d\u56fd\u9999\u6e2f", "\u4e2d\u56fd\u5927\u9646"], "genre": ["\u52a8\u4f5c", "\u7231\u60c5", "\u6b66\u4fa0", "\u53e4\u88c5"]}, {"index": 218, "title": "\u9752\u86c7", "director": ["\u5f90\u514b Hark Tsui"], "date": "1993", "region": ["\u4e2d\u56fd\u9999\u6e2f", "\u4e2d\u56fd\u5927\u9646"], "genre": ["\u5267\u60c5", "\u7231\u60c5", "\u5947\u5e7b", "\u53e4\u88c5"]}, {"index": 219, "title": "\u75af\u72c2\u7684\u9ea6\u514b\u65af4\uff1a\u72c2\u66b4\u4e4b\u8def", "director": ["\u4e54\u6cbb\u00b7\u7c73\u52d2 George Miller"], "date": "2015", "region": ["\u6fb3\u5927\u5229\u4e9a", "\u5357\u975e"], "genre": ["\u52a8\u4f5c", "\u79d1\u5e7b", "\u5192\u9669"]}, {"index": 220, "title": "\u65e0\u803b\u6df7\u86cb", "director": ["Quentin Tarantino"], "date": "2009", "region": ["\u5fb7\u56fd", "\u7f8e\u56fd"], "genre": ["\u5267\u60c5", "\u72af\u7f6a"]}, {"index": 221, "title": "\u6b65\u5c65\u4e0d\u505c", "director": ["\u662f\u679d\u88d5\u548c Hirokazu Koreeda"], "date": "2008", "region": ["\u65e5\u672c"], "genre": ["\u5267\u60c5", "\u5bb6\u5ead"]}, {"index": 222, "title": "\u8840\u94bb", "director": ["\u7231\u5fb7\u534e\u00b7\u5179\u5a01\u514b Edward Zwick"], "date": "2006", "region": ["\u7f8e\u56fd", "\u5fb7\u56fd", "\u82f1\u56fd"], "genre": ["\u5267\u60c5", "\u60ca\u609a", "\u5192\u9669"]}, {"index": 223, "title": "\u71c3\u60c5\u5c81\u6708", "director": ["\u7231\u5fb7\u534e\u00b7\u5179\u5a01\u514b Edward Zwick"], "date": "1994", "region": ["\u7f8e\u56fd"], "genre": ["\u5267\u60c5", "\u7231\u60c5", "\u6218\u4e89", "\u897f\u90e8"]}, {"index": 224, "title": "\u4e1c\u4eac\u6559\u7236", "director": ["\u4eca\u654f Satoshi Kon"], "date": "2003", "region": ["\u65e5\u672c"], "genre": ["\u5267\u60c5", "\u559c\u5267", "\u52a8\u753b"]}, {"index": 225, "title": "\u6d77\u6d0b", "director": ["\u96c5\u514b\u00b7\u8d1d\u6c49 Jacques Perrin", "\u96c5\u514b\u00b7\u514b\u9c81\u5965\u5fb7 Jacques Cluzaud"], "date": "2009", "region": ["\u6cd5\u56fd", "\u745e\u58eb", "\u897f\u73ed\u7259", "\u7f8e\u56fd", "\u963f\u8054\u914b", "\u6469\u7eb3\u54e5"], "genre": ["\u7eaa\u5f55\u7247"]}, {"index": 226, "title": "\u65e0\u95f4\u90532", "director": ["\u5218\u4f1f\u5f3a", "\u9ea6\u5146\u8f89"], "date": "2003", "region": ["\u4e2d\u56fd\u9999\u6e2f"], "genre": ["\u5267\u60c5", "\u72af\u7f6a", "\u60ca\u609a"]}, {"index": 227, "title": "\u5f57\u661f\u6765\u7684\u90a3\u4e00\u591c", "director": ["\u8a79\u59c6\u65af\u00b7\u6c83\u5fb7\u00b7\u5e03\u67ef\u7279 James Ward Byrkit"], "date": "2013", "region": ["\u7f8e\u56fd", "\u82f1\u56fd"], "genre": ["\u79d1\u5e7b", "\u60ac\u7591", "\u60ca\u609a"]}, {"index": 228, "title": "\u8c0d\u5f71\u91cd\u91cd2", "director": ["\u4fdd\u7f57\u00b7\u683c\u6797\u683c\u62c9\u65af Paul Greengrass"], "date": "2004", "region": ["\u7f8e\u56fd", "\u5fb7\u56fd"], "genre": ["\u52a8\u4f5c", "\u60ac\u7591", "\u60ca\u609a"]}, {"index": 229, "title": "\u7a7f\u8d8a\u65f6\u7a7a\u7684\u5c11\u5973", "director": ["\u7ec6\u7530\u5b88 Mamoru Hosoda"], "date": "2006", "region": ["\u65e5\u672c"], "genre": ["\u5267\u60c5", "\u7231\u60c5", "\u79d1\u5e7b", "\u52a8\u753b"]}, {"index": 230, "title": "\u6218\u4e89\u4e4b\u738b", "director": ["\u5b89\u5fb7\u9c81\u00b7\u5c3c\u79d1\u5c14 Andrew Niccol"], "date": "2005", "region": ["\u6cd5\u56fd", "\u5fb7\u56fd", "\u7f8e\u56fd"], "genre": ["\u5267\u60c5", "\u72af\u7f6a"]}, {"index": 231, "title": "\u963f\u98de\u6b63\u4f20", "director": ["\u738b\u5bb6\u536b Kar Wai Wong"], "date": "1990", "region": ["\u4e2d\u56fd\u9999\u6e2f"], "genre": ["\u72af\u7f6a", "\u5267\u60c5", "\u7231\u60c5"]}, {"index": 232, "title": "\u5730\u7403\u4e0a\u7684\u661f\u661f", "director": ["\u963f\u7c73\u5c14\u00b7\u6c57 Aamir Khan"], "date": "2007", "region": ["\u5370\u5ea6"], "genre": ["\u5267\u60c5", "\u513f\u7ae5", "\u5bb6\u5ead"]}, {"index": 233, "title": "\u5b8c\u7f8e\u964c\u751f\u4eba", "director": ["\u4fdd\u7f57\u00b7\u683c\u8bfa\u7ef4\u745f Paolo Genovese"], "date": "2016", "region": ["\u610f\u5927\u5229"], "genre": ["\u5267\u60c5", "\u559c\u5267"]}, {"index": 234, "title": "\u8c0d\u5f71\u91cd\u91cd", "director": ["\u9053\u683c\u00b7\u91cc\u66fc Doug Liman"], "date": "2002", "region": ["\u7f8e\u56fd", "\u5fb7\u56fd", "\u6377\u514b"], "genre": ["\u52a8\u4f5c", "\u60ac\u7591", "\u60ca\u609a"]}, {"index": 235, "title": "\u5343\u94a7\u4e00\u53d1", "director": ["\u5b89\u5fb7\u9c81\u00b7\u5c3c\u79d1\u5c14 Andrew Niccol"], "date": "1997", "region": ["\u7f8e\u56fd"], "genre": ["\u5267\u60c5", "\u79d1\u5e7b", "\u60ca\u609a"]}, {"index": 236, "title": "\u9999\u6c34", "director": ["\u6c64\u59c6\u00b7\u63d0\u514b\u5a01 Tom Tykwer"], "date": "2006", "region": ["\u5fb7\u56fd", "\u6cd5\u56fd", "\u897f\u73ed\u7259", "\u7f8e\u56fd"], "genre": ["\u5267\u60c5", "\u72af\u7f6a", "\u5947\u5e7b"]}, {"index": 237, "title": "\u4e1c\u4eac\u7269\u8bed", "director": ["\u5c0f\u6d25\u5b89\u4e8c\u90ce Yasujir\u00f4 Ozu"], "date": "1953", "region": ["\u65e5\u672c"], "genre": ["\u5267\u60c5", "\u5bb6\u5ead"]}, {"index": 238, "title": "\u9ed1\u5ba2\u5e1d\u56fd2\uff1a\u91cd\u88c5\u4e0a\u9635", "director": ["\u62c9\u5a1c\u00b7\u6c83\u5353\u65af\u57fa Lana Wachowski", "\u8389\u8389\u00b7\u6c83\u5353\u65af\u57fa Lilly Wachowski"], "date": "2003", "region": ["\u7f8e\u56fd"], "genre": ["\u52a8\u4f5c", "\u79d1\u5e7b"]}, {"index": 239, "title": "\u5d16\u4e0a\u7684\u6ce2\u599e", "director": ["\u5bab\u5d0e\u9a8f Hayao Miyazaki"], "date": "2008", "region": ["\u65e5\u672c"], "genre": ["\u52a8\u753b", "\u5947\u5e7b", "\u5192\u9669"]}, {"index": 240, "title": "\u6211\u7231\u4f60", "director": ["\u79cb\u660c\u6c11 Chang-min Choo"], "date": "2011", "region": ["\u97e9\u56fd"], "genre": ["\u5267\u60c5", "\u7231\u60c5"]}, {"index": 241, "title": "\u518d\u6b21\u51fa\u53d1\u4e4b\u7ebd\u7ea6\u9047\u89c1\u4f60", "director": ["\u7ea6\u7ff0\u00b7\u5361\u5c3c John Carney"], "date": "2013", "region": ["\u7f8e\u56fd"], "genre": ["\u559c\u5267", "\u7231\u60c5", "\u97f3\u4e50"]}, {"index": 242, "title": "\u6717\u8bfb\u8005", "director": ["\u53f2\u8482\u82ac\u00b7\u6234\u5fb7\u5229 Stephen Daldry"], "date": "2008", "region": ["\u7f8e\u56fd", "\u5fb7\u56fd"], "genre": ["\u5267\u60c5", "\u7231\u60c5"]}, {"index": 243, "title": "\u9a74\u5f97\u6c34", "director": ["\u5468\u7533 Shen Zhou", "\u5218\u9732 Lu Liu"], "date": "2016", "region": ["\u4e2d\u56fd\u5927\u9646"], "genre": ["\u5267\u60c5", "\u559c\u5267"]}, {"index": 244, "title": "\u805a\u7126", "director": ["\u6258\u9a6c\u65af\u00b7\u9ea6\u5361\u9521 Thomas McCarthy"], "date": "2015", "region": ["\u7f8e\u56fd"], "genre": ["\u5267\u60c5", "\u4f20\u8bb0"]}, {"index": 245, "title": "\u6d6a\u6f6e", "director": ["\u4e39\u5c3c\u65af\u00b7\u7518\u585e\u5c14 Dennis Gansel"], "date": "2008", "region": ["\u5fb7\u56fd"], "genre": ["\u5267\u60c5", "\u60ca\u609a"]}, {"index": 246, "title": "\u731c\u706b\u8f66", "director": ["\u4e39\u5c3c\u00b7\u535a\u4f0a\u5c14 Danny Boyle"], "date": "1996", "region": ["\u82f1\u56fd"], "genre": ["\u5267\u60c5", "\u72af\u7f6a"]}, {"index": 247, "title": "\u5c0f\u841d\u8389\u7684\u7334\u795e\u5927\u53d4", "director": ["\u5361\u6bd4\u5c14\u00b7\u6c57 Kabir Khan"], "date": "2015", "region": ["\u5370\u5ea6"], "genre": ["\u5267\u60c5", "\u559c\u5267", "\u52a8\u4f5c"]}, {"index": 248, "title": "\u8336\u9986", "director": ["\u8c22\u6dfb Tian Xie"], "date": "1982", "region": ["\u4e2d\u56fd\u5927\u9646"], "genre": ["\u5267\u60c5", "\u5386\u53f2"]}, {"index": 249, "title": "\u8ffd\u968f", "director": ["\u514b\u91cc\u65af\u6258\u5f17\u00b7\u8bfa\u5170 Christopher Nolan"], "date": "1998", "region": ["\u82f1\u56fd"], "genre": ["\u72af\u7f6a", "\u60ac\u7591", "\u60ca\u609a"]}, {"index": 250, "title": "\u9ed1\u9e70\u5760\u843d", "director": ["\u96f7\u5fb7\u5229\u00b7\u65af\u79d1\u7279 Ridley Scott"], "date": "2001", "region": ["\u7f8e\u56fd", "\u82f1\u56fd"], "genre": ["\u52a8\u4f5c", "\u5386\u53f2", "\u6218\u4e89"]}]